<cacti>	
	<hash_000019afc1e8ef7ae986ad9732f63180aba76e>
		<name>Available Updates</name>
		<graph>
			<t_title></t_title>
			<title>|host_description| - Available Updates</title>
			<t_image_format_id></t_image_format_id>
			<image_format_id>1</image_format_id>
			<t_height></t_height>
			<height>120</height>
			<t_width></t_width>
			<width>750</width>
			<t_slope_mode></t_slope_mode>
			<slope_mode>on</slope_mode>
			<t_auto_scale></t_auto_scale>
			<auto_scale>on</auto_scale>
			<t_auto_scale_opts></t_auto_scale_opts>
			<auto_scale_opts>2</auto_scale_opts>
			<t_auto_scale_log></t_auto_scale_log>
			<auto_scale_log></auto_scale_log>
			<t_scale_log_units></t_scale_log_units>
			<scale_log_units></scale_log_units>
			<t_auto_scale_rigid></t_auto_scale_rigid>
			<auto_scale_rigid></auto_scale_rigid>
			<t_auto_padding></t_auto_padding>
			<auto_padding>on</auto_padding>
			<t_export></t_export>
			<export>on</export>
			<t_upper_limit></t_upper_limit>
			<upper_limit>1</upper_limit>
			<t_lower_limit></t_lower_limit>
			<lower_limit>0</lower_limit>
			<t_base_value></t_base_value>
			<base_value>1000</base_value>
			<t_unit_value></t_unit_value>
			<unit_value></unit_value>
			<t_unit_exponent_value></t_unit_exponent_value>
			<unit_exponent_value></unit_exponent_value>
			<t_vertical_label></t_vertical_label>
			<vertical_label>Updates</vertical_label>
		</graph>
		<items>
			<hash_100019f443b3ec8f94af5cbbbb10a865824828>
				<task_item_id>hash_0800191702d7e9d25e63667ad79e501721a2e9</task_item_id>
				<color_id>FF7D00</color_id>
				<alpha>FF</alpha>
				<graph_type_id>7</graph_type_id>
				<consolidation_function_id>1</consolidation_function_id>
				<cdef_id>0</cdef_id>
				<value></value>
				<gprint_id>hash_06001919414480d6897c8731c7dc6c5310653e</gprint_id>
				<text_format>Security</text_format>
				<hard_return></hard_return>
				<sequence>1</sequence>
			</hash_100019f443b3ec8f94af5cbbbb10a865824828>
			<hash_1000197d926bafd580cc4ff6cd4d2d68ed69ce>
				<task_item_id>hash_0800191702d7e9d25e63667ad79e501721a2e9</task_item_id>
				<color_id>0</color_id>
				<alpha>FF</alpha>
				<graph_type_id>9</graph_type_id>
				<consolidation_function_id>4</consolidation_function_id>
				<cdef_id>0</cdef_id>
				<value></value>
				<gprint_id>hash_06001919414480d6897c8731c7dc6c5310653e</gprint_id>
				<text_format>Current:</text_format>
				<hard_return></hard_return>
				<sequence>5</sequence>
			</hash_1000197d926bafd580cc4ff6cd4d2d68ed69ce>
			<hash_100019d88b3cff14b03391c81d51e3d69b8f74>
				<task_item_id>hash_0800191702d7e9d25e63667ad79e501721a2e9</task_item_id>
				<color_id>0</color_id>
				<alpha>FF</alpha>
				<graph_type_id>9</graph_type_id>
				<consolidation_function_id>1</consolidation_function_id>
				<cdef_id>0</cdef_id>
				<value></value>
				<gprint_id>hash_06001919414480d6897c8731c7dc6c5310653e</gprint_id>
				<text_format>Average:</text_format>
				<hard_return></hard_return>
				<sequence>6</sequence>
			</hash_100019d88b3cff14b03391c81d51e3d69b8f74>
			<hash_1000192d06bf25497467c09179a24e25fad53d>
				<task_item_id>hash_0800191702d7e9d25e63667ad79e501721a2e9</task_item_id>
				<color_id>0</color_id>
				<alpha>FF</alpha>
				<graph_type_id>9</graph_type_id>
				<consolidation_function_id>3</consolidation_function_id>
				<cdef_id>0</cdef_id>
				<value></value>
				<gprint_id>hash_06001919414480d6897c8731c7dc6c5310653e</gprint_id>
				<text_format>Maximum:</text_format>
				<hard_return>on</hard_return>
				<sequence>7</sequence>
			</hash_1000192d06bf25497467c09179a24e25fad53d>
			<hash_1000198fc863a2fce2281b73c44e3f24cf1049>
				<task_item_id>hash_0800194effc8bba8149d5a1f390b45e7a2480b</task_item_id>
				<color_id>EACC00</color_id>
				<alpha>FF</alpha>
				<graph_type_id>8</graph_type_id>
				<consolidation_function_id>1</consolidation_function_id>
				<cdef_id>0</cdef_id>
				<value></value>
				<gprint_id>hash_06001919414480d6897c8731c7dc6c5310653e</gprint_id>
				<text_format>Non-Security</text_format>
				<hard_return></hard_return>
				<sequence>8</sequence>
			</hash_1000198fc863a2fce2281b73c44e3f24cf1049>
			<hash_1000199382b0c07e381698333b8f68415f2809>
				<task_item_id>hash_0800194effc8bba8149d5a1f390b45e7a2480b</task_item_id>
				<color_id>0</color_id>
				<alpha>FF</alpha>
				<graph_type_id>9</graph_type_id>
				<consolidation_function_id>4</consolidation_function_id>
				<cdef_id>0</cdef_id>
				<value></value>
				<gprint_id>hash_06001919414480d6897c8731c7dc6c5310653e</gprint_id>
				<text_format>Current:</text_format>
				<hard_return></hard_return>
				<sequence>9</sequence>
			</hash_1000199382b0c07e381698333b8f68415f2809>
			<hash_100019cf90c396b3ed7995acb547fae37044e5>
				<task_item_id>hash_0800194effc8bba8149d5a1f390b45e7a2480b</task_item_id>
				<color_id>0</color_id>
				<alpha>FF</alpha>
				<graph_type_id>9</graph_type_id>
				<consolidation_function_id>1</consolidation_function_id>
				<cdef_id>0</cdef_id>
				<value></value>
				<gprint_id>hash_06001919414480d6897c8731c7dc6c5310653e</gprint_id>
				<text_format>Average:</text_format>
				<hard_return></hard_return>
				<sequence>10</sequence>
			</hash_100019cf90c396b3ed7995acb547fae37044e5>
			<hash_100019ab1690818a80b79e24ab1f817b07ae94>
				<task_item_id>hash_0800194effc8bba8149d5a1f390b45e7a2480b</task_item_id>
				<color_id>0</color_id>
				<alpha>FF</alpha>
				<graph_type_id>9</graph_type_id>
				<consolidation_function_id>3</consolidation_function_id>
				<cdef_id>0</cdef_id>
				<value></value>
				<gprint_id>hash_06001919414480d6897c8731c7dc6c5310653e</gprint_id>
				<text_format>Maximum:</text_format>
				<hard_return>on</hard_return>
				<sequence>11</sequence>
			</hash_100019ab1690818a80b79e24ab1f817b07ae94>
			<hash_100019b0ef438e6fd12ae3174d77ec9066fc21>
				<task_item_id>hash_080019e3e5a54d053f37488b01a6cabe36bf25</task_item_id>
				<color_id>B11D03</color_id>
				<alpha>FF</alpha>
				<graph_type_id>5</graph_type_id>
				<consolidation_function_id>1</consolidation_function_id>
				<cdef_id>0</cdef_id>
				<value></value>
				<gprint_id>hash_06001919414480d6897c8731c7dc6c5310653e</gprint_id>
				<text_format>Total</text_format>
				<hard_return></hard_return>
				<sequence>12</sequence>
			</hash_100019b0ef438e6fd12ae3174d77ec9066fc21>
			<hash_10001999ce1b746da3a3dec05e2d953763f203>
				<task_item_id>hash_080019e3e5a54d053f37488b01a6cabe36bf25</task_item_id>
				<color_id>0</color_id>
				<alpha>FF</alpha>
				<graph_type_id>9</graph_type_id>
				<consolidation_function_id>4</consolidation_function_id>
				<cdef_id>0</cdef_id>
				<value></value>
				<gprint_id>hash_06001919414480d6897c8731c7dc6c5310653e</gprint_id>
				<text_format>Current:</text_format>
				<hard_return></hard_return>
				<sequence>13</sequence>
			</hash_10001999ce1b746da3a3dec05e2d953763f203>
			<hash_100019543dea041864e09cae0788025b3610e8>
				<task_item_id>hash_080019e3e5a54d053f37488b01a6cabe36bf25</task_item_id>
				<color_id>0</color_id>
				<alpha>FF</alpha>
				<graph_type_id>9</graph_type_id>
				<consolidation_function_id>1</consolidation_function_id>
				<cdef_id>0</cdef_id>
				<value></value>
				<gprint_id>hash_06001919414480d6897c8731c7dc6c5310653e</gprint_id>
				<text_format>Average:</text_format>
				<hard_return></hard_return>
				<sequence>14</sequence>
			</hash_100019543dea041864e09cae0788025b3610e8>
			<hash_1000193ec6a8d0310fe449e4041cc755c83fa1>
				<task_item_id>hash_080019e3e5a54d053f37488b01a6cabe36bf25</task_item_id>
				<color_id>0</color_id>
				<alpha>FF</alpha>
				<graph_type_id>9</graph_type_id>
				<consolidation_function_id>3</consolidation_function_id>
				<cdef_id>0</cdef_id>
				<value></value>
				<gprint_id>hash_06001919414480d6897c8731c7dc6c5310653e</gprint_id>
				<text_format>Maximum:</text_format>
				<hard_return>on</hard_return>
				<sequence>15</sequence>
			</hash_1000193ec6a8d0310fe449e4041cc755c83fa1>
		</items>
		<inputs>
			<hash_0900190fe6e3459c39e08d70848cc1ba725fc3>
				<name>Data Source Available Updates Total</name>
				<description></description>
				<column_name>task_item_id</column_name>
				<items>hash_000019b0ef438e6fd12ae3174d77ec9066fc21|hash_00001999ce1b746da3a3dec05e2d953763f203|hash_000019543dea041864e09cae0788025b3610e8|hash_0000193ec6a8d0310fe449e4041cc755c83fa1</items>
			</hash_0900190fe6e3459c39e08d70848cc1ba725fc3>
			<hash_090019b300a754b9657847b66c4c9f43e06465>
				<name>Data Source Available Updates Non Security</name>
				<description></description>
				<column_name>task_item_id</column_name>
				<items>hash_0000198fc863a2fce2281b73c44e3f24cf1049|hash_0000199382b0c07e381698333b8f68415f2809|hash_000019cf90c396b3ed7995acb547fae37044e5|hash_000019ab1690818a80b79e24ab1f817b07ae94</items>
			</hash_090019b300a754b9657847b66c4c9f43e06465>
			<hash_09001920e065de20b73ef62f13e35bdfb7a534>
				<name>Data Source Available Updates Security</name>
				<description></description>
				<column_name>task_item_id</column_name>
				<items>hash_000019f443b3ec8f94af5cbbbb10a865824828|hash_000019d88b3cff14b03391c81d51e3d69b8f74|hash_0000197d926bafd580cc4ff6cd4d2d68ed69ce|hash_0000192d06bf25497467c09179a24e25fad53d</items>
			</hash_09001920e065de20b73ef62f13e35bdfb7a534>
		</inputs>
	</hash_000019afc1e8ef7ae986ad9732f63180aba76e>
	<hash_01001998ebfbe1ec1205be27b457b758a1839f>
		<name>Available Updates Total</name>
		<ds>
			<t_name></t_name>
			<name>|host_description| - Available Updates Total</name>
			<data_input_id>hash_0300193eb92bb845b9660a7445cf9740726522</data_input_id>
			<t_rra_id></t_rra_id>
			<t_rrd_step></t_rrd_step>
			<rrd_step>300</rrd_step>
			<t_active></t_active>
			<active>on</active>
			<rra_items>hash_150019c21df5178e5c955013591239eb0afd46|hash_1500190d9c0af8b8acdc7807943937b3208e29|hash_1500196fc2d038fb42950138b0ce3e9874cc60|hash_150019e36f3adb9f152adfa5dc50fd2b23337e|hash_150019283ea2bf1634d92ce081ec82a634f513</rra_items>
		</ds>
		<items>
			<hash_080019e3e5a54d053f37488b01a6cabe36bf25>
				<t_data_source_name></t_data_source_name>
				<data_source_name>au_total</data_source_name>
				<t_rrd_minimum></t_rrd_minimum>
				<rrd_minimum>0</rrd_minimum>
				<t_rrd_maximum></t_rrd_maximum>
				<rrd_maximum>1000</rrd_maximum>
				<t_data_source_type_id></t_data_source_type_id>
				<data_source_type_id>1</data_source_type_id>
				<t_rrd_heartbeat></t_rrd_heartbeat>
				<rrd_heartbeat>600</rrd_heartbeat>
				<t_data_input_field_id></t_data_input_field_id>
				<data_input_field_id>0</data_input_field_id>
			</hash_080019e3e5a54d053f37488b01a6cabe36bf25>
		</items>
		<data>
			<item_000>
				<data_input_field_id>hash_070019135a77685aa01abf1f6e752fe1e3c7f2</data_input_field_id>
				<t_value></t_value>
				<value></value>
			</item_000>
			<item_001>
				<data_input_field_id>hash_070019d94caa7cc3733bd95ee00a3917fdcbb5</data_input_field_id>
				<t_value></t_value>
				<value></value>
			</item_001>
			<item_002>
				<data_input_field_id>hash_070019feda162701240101bc74148415ef415a</data_input_field_id>
				<t_value></t_value>
				<value></value>
			</item_002>
			<item_003>
				<data_input_field_id>hash_070019c60c9aac1e1b3555ea0620b8bbfd82cb</data_input_field_id>
				<t_value></t_value>
				<value></value>
			</item_003>
			<item_004>
				<data_input_field_id>hash_07001920832ce12f099c8e54140793a091af90</data_input_field_id>
				<t_value></t_value>
				<value></value>
			</item_004>
			<item_005>
				<data_input_field_id>hash_0700194276a5ec6e3fe33995129041b1909762</data_input_field_id>
				<t_value></t_value>
				<value>1.3.6.1.4.1.8072.1.3.2.4.1.2.7.117.112.100.97.116.101.115.1</value>
			</item_005>
			<item_006>
				<data_input_field_id>hash_070019fc64b99742ec417cc424dbf8c7692d36</data_input_field_id>
				<t_value></t_value>
				<value></value>
			</item_006>
			<item_007>
				<data_input_field_id>hash_070019012ccb1d3687d3edb29c002ea66e72da</data_input_field_id>
				<t_value></t_value>
				<value></value>
			</item_007>
			<item_008>
				<data_input_field_id>hash_0700199c55a74bd571b4f00a96fd4b793278c6</data_input_field_id>
				<t_value></t_value>
				<value></value>
			</item_008>
			<item_009>
				<data_input_field_id>hash_070019ad14ac90641aed388139f6ba86a2e48b</data_input_field_id>
				<t_value></t_value>
				<value></value>
			</item_009>
			<item_010>
				<data_input_field_id>hash_07001932285d5bf16e56c478f5e83f32cda9ef</data_input_field_id>
				<t_value></t_value>
				<value></value>
			</item_010>
			<item_011>
				<data_input_field_id>hash_07001992f5906c8dc0f964b41f4253df582c38</data_input_field_id>
				<t_value></t_value>
				<value></value>
			</item_011>
		</data>
	</hash_01001998ebfbe1ec1205be27b457b758a1839f>
	<hash_0100190bc33cc55134db16a5c4e30fee77c594>
		<name>Available Updates Security</name>
		<ds>
			<t_name></t_name>
			<name>|host_description| - Available Updates Security</name>
			<data_input_id>hash_0300193eb92bb845b9660a7445cf9740726522</data_input_id>
			<t_rra_id></t_rra_id>
			<t_rrd_step></t_rrd_step>
			<rrd_step>300</rrd_step>
			<t_active></t_active>
			<active>on</active>
			<rra_items>hash_150019c21df5178e5c955013591239eb0afd46|hash_1500190d9c0af8b8acdc7807943937b3208e29|hash_1500196fc2d038fb42950138b0ce3e9874cc60|hash_150019e36f3adb9f152adfa5dc50fd2b23337e|hash_150019283ea2bf1634d92ce081ec82a634f513</rra_items>
		</ds>
		<items>
			<hash_0800191702d7e9d25e63667ad79e501721a2e9>
				<t_data_source_name></t_data_source_name>
				<data_source_name>au_sec</data_source_name>
				<t_rrd_minimum></t_rrd_minimum>
				<rrd_minimum>0</rrd_minimum>
				<t_rrd_maximum></t_rrd_maximum>
				<rrd_maximum>1000</rrd_maximum>
				<t_data_source_type_id></t_data_source_type_id>
				<data_source_type_id>1</data_source_type_id>
				<t_rrd_heartbeat></t_rrd_heartbeat>
				<rrd_heartbeat>600</rrd_heartbeat>
				<t_data_input_field_id></t_data_input_field_id>
				<data_input_field_id>0</data_input_field_id>
			</hash_0800191702d7e9d25e63667ad79e501721a2e9>
		</items>
		<data>
			<item_000>
				<data_input_field_id>hash_070019135a77685aa01abf1f6e752fe1e3c7f2</data_input_field_id>
				<t_value></t_value>
				<value></value>
			</item_000>
			<item_001>
				<data_input_field_id>hash_07001992f5906c8dc0f964b41f4253df582c38</data_input_field_id>
				<t_value></t_value>
				<value></value>
			</item_001>
			<item_002>
				<data_input_field_id>hash_07001932285d5bf16e56c478f5e83f32cda9ef</data_input_field_id>
				<t_value></t_value>
				<value></value>
			</item_002>
			<item_003>
				<data_input_field_id>hash_070019ad14ac90641aed388139f6ba86a2e48b</data_input_field_id>
				<t_value></t_value>
				<value></value>
			</item_003>
			<item_004>
				<data_input_field_id>hash_0700199c55a74bd571b4f00a96fd4b793278c6</data_input_field_id>
				<t_value></t_value>
				<value></value>
			</item_004>
			<item_005>
				<data_input_field_id>hash_070019012ccb1d3687d3edb29c002ea66e72da</data_input_field_id>
				<t_value></t_value>
				<value></value>
			</item_005>
			<item_006>
				<data_input_field_id>hash_0700194276a5ec6e3fe33995129041b1909762</data_input_field_id>
				<t_value></t_value>
				<value>1.3.6.1.4.1.8072.1.3.2.4.1.2.7.117.112.100.97.116.101.115.2</value>
			</item_006>
			<item_007>
				<data_input_field_id>hash_070019fc64b99742ec417cc424dbf8c7692d36</data_input_field_id>
				<t_value></t_value>
				<value></value>
			</item_007>
			<item_008>
				<data_input_field_id>hash_07001920832ce12f099c8e54140793a091af90</data_input_field_id>
				<t_value></t_value>
				<value></value>
			</item_008>
			<item_009>
				<data_input_field_id>hash_070019c60c9aac1e1b3555ea0620b8bbfd82cb</data_input_field_id>
				<t_value></t_value>
				<value></value>
			</item_009>
			<item_010>
				<data_input_field_id>hash_070019feda162701240101bc74148415ef415a</data_input_field_id>
				<t_value></t_value>
				<value></value>
			</item_010>
			<item_011>
				<data_input_field_id>hash_070019d94caa7cc3733bd95ee00a3917fdcbb5</data_input_field_id>
				<t_value></t_value>
				<value></value>
			</item_011>
		</data>
	</hash_0100190bc33cc55134db16a5c4e30fee77c594>
	<hash_0100193a8f4f6940e7d15c2631085f207ea046>
		<name>Available Updates Non Security</name>
		<ds>
			<t_name></t_name>
			<name>|host_description| - Available Updates Non Security</name>
			<data_input_id>hash_0300193eb92bb845b9660a7445cf9740726522</data_input_id>
			<t_rra_id></t_rra_id>
			<t_rrd_step></t_rrd_step>
			<rrd_step>300</rrd_step>
			<t_active></t_active>
			<active>on</active>
			<rra_items>hash_150019c21df5178e5c955013591239eb0afd46|hash_1500190d9c0af8b8acdc7807943937b3208e29|hash_1500196fc2d038fb42950138b0ce3e9874cc60|hash_150019e36f3adb9f152adfa5dc50fd2b23337e|hash_150019283ea2bf1634d92ce081ec82a634f513</rra_items>
		</ds>
		<items>
			<hash_0800194effc8bba8149d5a1f390b45e7a2480b>
				<t_data_source_name></t_data_source_name>
				<data_source_name>au_non_sec</data_source_name>
				<t_rrd_minimum></t_rrd_minimum>
				<rrd_minimum>0</rrd_minimum>
				<t_rrd_maximum></t_rrd_maximum>
				<rrd_maximum>1000</rrd_maximum>
				<t_data_source_type_id></t_data_source_type_id>
				<data_source_type_id>1</data_source_type_id>
				<t_rrd_heartbeat></t_rrd_heartbeat>
				<rrd_heartbeat>600</rrd_heartbeat>
				<t_data_input_field_id></t_data_input_field_id>
				<data_input_field_id>0</data_input_field_id>
			</hash_0800194effc8bba8149d5a1f390b45e7a2480b>
		</items>
		<data>
			<item_000>
				<data_input_field_id>hash_070019feda162701240101bc74148415ef415a</data_input_field_id>
				<t_value></t_value>
				<value></value>
			</item_000>
			<item_001>
				<data_input_field_id>hash_070019d94caa7cc3733bd95ee00a3917fdcbb5</data_input_field_id>
				<t_value></t_value>
				<value></value>
			</item_001>
			<item_002>
				<data_input_field_id>hash_070019fc64b99742ec417cc424dbf8c7692d36</data_input_field_id>
				<t_value></t_value>
				<value></value>
			</item_002>
			<item_003>
				<data_input_field_id>hash_070019135a77685aa01abf1f6e752fe1e3c7f2</data_input_field_id>
				<t_value></t_value>
				<value></value>
			</item_003>
			<item_004>
				<data_input_field_id>hash_07001920832ce12f099c8e54140793a091af90</data_input_field_id>
				<t_value></t_value>
				<value></value>
			</item_004>
			<item_005>
				<data_input_field_id>hash_070019c60c9aac1e1b3555ea0620b8bbfd82cb</data_input_field_id>
				<t_value></t_value>
				<value></value>
			</item_005>
			<item_006>
				<data_input_field_id>hash_0700194276a5ec6e3fe33995129041b1909762</data_input_field_id>
				<t_value></t_value>
				<value>1.3.6.1.4.1.8072.1.3.2.4.1.2.7.117.112.100.97.116.101.115.3</value>
			</item_006>
			<item_007>
				<data_input_field_id>hash_070019012ccb1d3687d3edb29c002ea66e72da</data_input_field_id>
				<t_value></t_value>
				<value></value>
			</item_007>
			<item_008>
				<data_input_field_id>hash_0700199c55a74bd571b4f00a96fd4b793278c6</data_input_field_id>
				<t_value></t_value>
				<value></value>
			</item_008>
			<item_009>
				<data_input_field_id>hash_070019ad14ac90641aed388139f6ba86a2e48b</data_input_field_id>
				<t_value></t_value>
				<value></value>
			</item_009>
			<item_010>
				<data_input_field_id>hash_07001932285d5bf16e56c478f5e83f32cda9ef</data_input_field_id>
				<t_value></t_value>
				<value></value>
			</item_010>
			<item_011>
				<data_input_field_id>hash_07001992f5906c8dc0f964b41f4253df582c38</data_input_field_id>
				<t_value></t_value>
				<value></value>
			</item_011>
		</data>
	</hash_0100193a8f4f6940e7d15c2631085f207ea046>
	<hash_0300193eb92bb845b9660a7445cf9740726522>
		<name>Get SNMP Data</name>
		<type_id>2</type_id>
		<input_string></input_string>
		<fields>
			<hash_07001992f5906c8dc0f964b41f4253df582c38>
				<name>SNMP IP Address</name>
				<update_rra></update_rra>
				<regexp_match></regexp_match>
				<allow_nulls></allow_nulls>
				<type_code>hostname</type_code>
				<input_output>in</input_output>
				<data_name>management_ip</data_name>
			</hash_07001992f5906c8dc0f964b41f4253df582c38>
			<hash_07001932285d5bf16e56c478f5e83f32cda9ef>
				<name>SNMP Community</name>
				<update_rra></update_rra>
				<regexp_match></regexp_match>
				<allow_nulls></allow_nulls>
				<type_code>snmp_community</type_code>
				<input_output>in</input_output>
				<data_name>snmp_community</data_name>
			</hash_07001932285d5bf16e56c478f5e83f32cda9ef>
			<hash_070019ad14ac90641aed388139f6ba86a2e48b>
				<name>SNMP Username</name>
				<update_rra></update_rra>
				<regexp_match></regexp_match>
				<allow_nulls>on</allow_nulls>
				<type_code>snmp_username</type_code>
				<input_output>in</input_output>
				<data_name>snmp_username</data_name>
			</hash_070019ad14ac90641aed388139f6ba86a2e48b>
			<hash_0700199c55a74bd571b4f00a96fd4b793278c6>
				<name>SNMP Password</name>
				<update_rra></update_rra>
				<regexp_match></regexp_match>
				<allow_nulls>on</allow_nulls>
				<type_code>snmp_password</type_code>
				<input_output>in</input_output>
				<data_name>snmp_password</data_name>
			</hash_0700199c55a74bd571b4f00a96fd4b793278c6>
			<hash_070019012ccb1d3687d3edb29c002ea66e72da>
				<name>SNMP Version (1, 2, or 3)</name>
				<update_rra></update_rra>
				<regexp_match></regexp_match>
				<allow_nulls>on</allow_nulls>
				<type_code>snmp_version</type_code>
				<input_output>in</input_output>
				<data_name>snmp_version</data_name>
			</hash_070019012ccb1d3687d3edb29c002ea66e72da>
			<hash_0700194276a5ec6e3fe33995129041b1909762>
				<name>OID</name>
				<update_rra></update_rra>
				<regexp_match></regexp_match>
				<allow_nulls></allow_nulls>
				<type_code>snmp_oid</type_code>
				<input_output>in</input_output>
				<data_name>oid</data_name>
			</hash_0700194276a5ec6e3fe33995129041b1909762>
			<hash_070019fc64b99742ec417cc424dbf8c7692d36>
				<name>SNMP Port</name>
				<update_rra></update_rra>
				<regexp_match></regexp_match>
				<allow_nulls></allow_nulls>
				<type_code>snmp_port</type_code>
				<input_output>in</input_output>
				<data_name>snmp_port</data_name>
			</hash_070019fc64b99742ec417cc424dbf8c7692d36>
			<hash_07001920832ce12f099c8e54140793a091af90>
				<name>SNMP Authenticaion Protocol (v3)</name>
				<update_rra></update_rra>
				<regexp_match></regexp_match>
				<allow_nulls></allow_nulls>
				<type_code>snmp_auth_protocol</type_code>
				<input_output>in</input_output>
				<data_name>snmp_auth_protocol</data_name>
			</hash_07001920832ce12f099c8e54140793a091af90>
			<hash_070019c60c9aac1e1b3555ea0620b8bbfd82cb>
				<name>SNMP Privacy Passphrase (v3)</name>
				<update_rra></update_rra>
				<regexp_match></regexp_match>
				<allow_nulls></allow_nulls>
				<type_code>snmp_priv_passphrase</type_code>
				<input_output>in</input_output>
				<data_name>snmp_priv_passphrase</data_name>
			</hash_070019c60c9aac1e1b3555ea0620b8bbfd82cb>
			<hash_070019feda162701240101bc74148415ef415a>
				<name>SNMP Privacy Protocol (v3)</name>
				<update_rra></update_rra>
				<regexp_match></regexp_match>
				<allow_nulls></allow_nulls>
				<type_code>snmp_priv_protocol</type_code>
				<input_output>in</input_output>
				<data_name>snmp_priv_protocol</data_name>
			</hash_070019feda162701240101bc74148415ef415a>
			<hash_070019d94caa7cc3733bd95ee00a3917fdcbb5>
				<name>SNMP Port</name>
				<update_rra></update_rra>
				<regexp_match></regexp_match>
				<allow_nulls>on</allow_nulls>
				<type_code>snmp_port</type_code>
				<input_output>in</input_output>
				<data_name>snmp_port</data_name>
			</hash_070019d94caa7cc3733bd95ee00a3917fdcbb5>
			<hash_070019135a77685aa01abf1f6e752fe1e3c7f2>
				<name>SNMP Port</name>
				<update_rra></update_rra>
				<regexp_match></regexp_match>
				<allow_nulls></allow_nulls>
				<type_code>snmp_port</type_code>
				<input_output>in</input_output>
				<data_name>snmp_port</data_name>
			</hash_070019135a77685aa01abf1f6e752fe1e3c7f2>
		</fields>
	</hash_0300193eb92bb845b9660a7445cf9740726522>
	<hash_150019c21df5178e5c955013591239eb0afd46>
		<name>Daily (5 Minute Average)</name>
		<x_files_factor>0.5</x_files_factor>
		<steps>1</steps>
		<rows>600</rows>
		<timespan>86400</timespan>
		<cf_items>1|3</cf_items>
	</hash_150019c21df5178e5c955013591239eb0afd46>
	<hash_1500190d9c0af8b8acdc7807943937b3208e29>
		<name>Weekly (30 Minute Average)</name>
		<x_files_factor>0.5</x_files_factor>
		<steps>6</steps>
		<rows>700</rows>
		<timespan>604800</timespan>
		<cf_items>1|3</cf_items>
	</hash_1500190d9c0af8b8acdc7807943937b3208e29>
	<hash_1500196fc2d038fb42950138b0ce3e9874cc60>
		<name>Monthly (2 Hour Average)</name>
		<x_files_factor>0.5</x_files_factor>
		<steps>24</steps>
		<rows>775</rows>
		<timespan>2678400</timespan>
		<cf_items>1|3</cf_items>
	</hash_1500196fc2d038fb42950138b0ce3e9874cc60>
	<hash_150019e36f3adb9f152adfa5dc50fd2b23337e>
		<name>Yearly (1 Day Average)</name>
		<x_files_factor>0.5</x_files_factor>
		<steps>288</steps>
		<rows>797</rows>
		<timespan>33053184</timespan>
		<cf_items>1|3</cf_items>
	</hash_150019e36f3adb9f152adfa5dc50fd2b23337e>
	<hash_150019283ea2bf1634d92ce081ec82a634f513>
		<name>Hourly (1 Minute Average)</name>
		<x_files_factor>0.5</x_files_factor>
		<steps>1</steps>
		<rows>500</rows>
		<timespan>14400</timespan>
		<cf_items>1|3</cf_items>
	</hash_150019283ea2bf1634d92ce081ec82a634f513>
	<hash_06001919414480d6897c8731c7dc6c5310653e>
		<name>Exact Numbers</name>
		<gprint_text>%8.0lf</gprint_text>
	</hash_06001919414480d6897c8731c7dc6c5310653e>
</cacti>